hmd_entity_storage/__init__.py
hmd_entity_storage/gremlin_query_support.py
hmd_entity_storage/hmd_entity_storage.py
hmd_entity_storage/alembic/README
hmd_entity_storage/alembic/alembic.ini
hmd_entity_storage/alembic/env.py
hmd_entity_storage/alembic/script.py.mako
hmd_entity_storage/alembic/__pycache__/env.cpython-311.pyc
hmd_entity_storage/alembic/versions/12cdb83620a9_add_relationship.py
hmd_entity_storage/alembic/versions/629c5f7dc7b3_create_relationship_from_to_indexes.py
hmd_entity_storage/alembic/versions/91c9eec02046_name_to_entity.py
hmd_entity_storage/alembic/versions/affe724897f1_initial_tables.py
hmd_entity_storage/alembic/versions/bdf0a12db196_add_name_index.py
hmd_entity_storage/alembic/versions/ffffc821fb8a_create_is_deleted_indexes.py
hmd_entity_storage/alembic/versions/__pycache__/12cdb83620a9_add_relationship.cpython-311.pyc
hmd_entity_storage/alembic/versions/__pycache__/629c5f7dc7b3_create_relationship_from_to_indexes.cpython-311.pyc
hmd_entity_storage/alembic/versions/__pycache__/91c9eec02046_name_to_entity.cpython-311.pyc
hmd_entity_storage/alembic/versions/__pycache__/affe724897f1_initial_tables.cpython-311.pyc
hmd_entity_storage/alembic/versions/__pycache__/bdf0a12db196_add_name_index.cpython-311.pyc
hmd_entity_storage/alembic/versions/__pycache__/ffffc821fb8a_create_is_deleted_indexes.cpython-311.pyc
hmd_entity_storage/auditor/__init__.py
hmd_entity_storage/auditor/engine_auditor.py
hmd_entity_storage/engines/__init__.py
hmd_entity_storage/engines/base_engine.py
hmd_entity_storage/engines/dynamodb_engine.py
hmd_entity_storage/engines/gremlin_engine.py
hmd_entity_storage/engines/postgres_engine.py
hmd_entity_storage/engines/sqlite_engine.py
hmd_entity_storage/utils/__init__.py
hmd_entity_storage/utils/sqlite_utils.py
hmd_entity_storage-0.2.315.dist-info/METADATA
hmd_entity_storage-0.2.315.dist-info/WHEEL
hmd_entity_storage-0.2.315.dist-info/top_level.txt
hmd_entity_storage-0.2.315.dist-info/RECORD
